py_agent_search/__init__.py
py_agent_search/agent.py
py_agent_search/log.py
py_agent_search/memory.py
py_agent_search/prompt.py
py_agent_search/state.py
py_agent_search/stream.py
py_agent_search/tools.py
py_agent_search-1.0.2.dist-info/licenses/LICENSE.md
py_agent_search-1.0.2.dist-info/METADATA
py_agent_search-1.0.2.dist-info/WHEEL
py_agent_search-1.0.2.dist-info/top_level.txt
py_agent_search-1.0.2.dist-info/RECORD
