Metadata-Version: 2.4
Name: py_agent_search
Version: 1.0.2
Summary: A Python package for agent ai to search in the web, wikipedia and youtube
Author-email: Giuseppe Zileni <giuseppe.zileni@gmail.com>
Keywords: langgraph,agent ai,search,web search,wikipedia search,youtube search,langchain
Classifier: Programming Language :: Python :: 3
Classifier: Operating System :: OS Independent
Requires-Python: >=3.9
License-File: LICENSE.md
Requires-Dist: aiohappyeyeballs==2.6.1
Requires-Dist: aiohttp==3.12.6
Requires-Dist: aiosignal==1.3.2
Requires-Dist: annotated-types==0.7.0
Requires-Dist: anthropic==0.52.2
Requires-Dist: anyio==4.9.0
Requires-Dist: appnope==0.1.4
Requires-Dist: asttokens==3.0.0
Requires-Dist: attrs==25.3.0
Requires-Dist: beautifulsoup4==4.13.4
Requires-Dist: build==1.2.2.post1
Requires-Dist: certifi==2025.4.26
Requires-Dist: charset-normalizer==3.4.2
Requires-Dist: click==8.2.1
Requires-Dist: comm==0.2.2
Requires-Dist: dataclasses-json==0.6.7
Requires-Dist: debugpy==1.8.14
Requires-Dist: decorator==5.2.1
Requires-Dist: distro==1.9.0
Requires-Dist: docutils==0.21.2
Requires-Dist: duckduckgo_search==8.0.2
Requires-Dist: dydantic==0.0.8
Requires-Dist: executing==2.2.0
Requires-Dist: frozenlist==1.6.0
Requires-Dist: greenlet==3.2.2
Requires-Dist: h11==0.16.0
Requires-Dist: httpcore==1.0.9
Requires-Dist: httpx==0.28.1
Requires-Dist: httpx-sse==0.4.0
Requires-Dist: id==1.5.0
Requires-Dist: idna==3.10
Requires-Dist: ipykernel==6.29.5
Requires-Dist: ipython==9.2.0
Requires-Dist: ipython_pygments_lexers==1.1.1
Requires-Dist: jaraco.classes==3.4.0
Requires-Dist: jaraco.context==6.0.1
Requires-Dist: jaraco.functools==4.1.0
Requires-Dist: jedi==0.19.2
Requires-Dist: jiter==0.10.0
Requires-Dist: jsonpatch==1.33
Requires-Dist: jsonpointer==3.0.0
Requires-Dist: jupyter_client==8.6.3
Requires-Dist: jupyter_core==5.8.1
Requires-Dist: keyring==25.6.0
Requires-Dist: langchain==0.3.25
Requires-Dist: langchain-anthropic==0.3.14
Requires-Dist: langchain-community==0.3.24
Requires-Dist: langchain-core==0.3.63
Requires-Dist: langchain-openai==0.3.18
Requires-Dist: langchain-text-splitters==0.3.8
Requires-Dist: langgraph==0.4.7
Requires-Dist: langgraph-checkpoint==2.0.26
Requires-Dist: langgraph-prebuilt==0.2.2
Requires-Dist: langgraph-sdk==0.1.70
Requires-Dist: langmem==0.0.27
Requires-Dist: langsmith==0.3.43
Requires-Dist: loki-logger-handler==1.1.2
Requires-Dist: lxml==5.4.0
Requires-Dist: markdown-it-py==3.0.0
Requires-Dist: marshmallow==3.26.1
Requires-Dist: matplotlib-inline==0.1.7
Requires-Dist: mdurl==0.1.2
Requires-Dist: more-itertools==10.7.0
Requires-Dist: multidict==6.4.4
Requires-Dist: mypy_extensions==1.1.0
Requires-Dist: nest-asyncio==1.6.0
Requires-Dist: nh3==0.2.21
Requires-Dist: numpy==2.2.6
Requires-Dist: openai==1.82.1
Requires-Dist: orjson==3.10.18
Requires-Dist: ormsgpack==1.10.0
Requires-Dist: packaging==24.2
Requires-Dist: parso==0.8.4
Requires-Dist: pexpect==4.9.0
Requires-Dist: platformdirs==4.3.8
Requires-Dist: primp==0.15.0
Requires-Dist: prompt_toolkit==3.0.51
Requires-Dist: propcache==0.3.1
Requires-Dist: psutil==7.0.0
Requires-Dist: ptyprocess==0.7.0
Requires-Dist: pure_eval==0.2.3
Requires-Dist: pydantic==2.11.5
Requires-Dist: pydantic-settings==2.9.1
Requires-Dist: pydantic_core==2.33.2
Requires-Dist: Pygments==2.19.1
Requires-Dist: pyproject_hooks==1.2.0
Requires-Dist: python-dateutil==2.9.0.post0
Requires-Dist: python-dotenv==1.1.0
Requires-Dist: PyYAML==6.0.2
Requires-Dist: pyzmq==26.4.0
Requires-Dist: readme_renderer==44.0
Requires-Dist: redis==6.2.0
Requires-Dist: regex==2024.11.6
Requires-Dist: requests==2.32.3
Requires-Dist: requests-toolbelt==1.0.0
Requires-Dist: rfc3986==2.0.0
Requires-Dist: rich==14.0.0
Requires-Dist: setuptools==80.9.0
Requires-Dist: six==1.17.0
Requires-Dist: sniffio==1.3.1
Requires-Dist: soupsieve==2.7
Requires-Dist: SQLAlchemy==2.0.41
Requires-Dist: stack-data==0.6.3
Requires-Dist: tenacity==9.1.2
Requires-Dist: tiktoken==0.9.0
Requires-Dist: tornado==6.5.1
Requires-Dist: tqdm==4.67.1
Requires-Dist: traitlets==5.14.3
Requires-Dist: trustcall==0.0.39
Requires-Dist: twine==6.1.0
Requires-Dist: typing-inspect==0.9.0
Requires-Dist: typing-inspection==0.4.1
Requires-Dist: typing_extensions==4.13.2
Requires-Dist: urllib3==2.4.0
Requires-Dist: wcwidth==0.2.13
Requires-Dist: wheel==0.45.1
Requires-Dist: wikipedia==1.4.0
Requires-Dist: xxhash==3.5.0
Requires-Dist: yarl==1.20.0
Requires-Dist: youtube-search==2.1.2
Requires-Dist: zstandard==0.23.0
Dynamic: license-file
